thop/__init__.py
thop/__version__.py
thop/fx_profile.py
thop/onnx_profile.py
thop/profile.py
thop/rnn_hooks.py
thop/utils.py
thop/vision/__init__.py
thop/vision/basic_hooks.py
thop/vision/calc_func.py
thop/vision/efficientnet.py
thop/vision/onnx_counter.py
hf_torrents-0.0.1.post2311281817.dist-info/LICENSE
hf_torrents-0.0.1.post2311281817.dist-info/METADATA
hf_torrents-0.0.1.post2311281817.dist-info/WHEEL
hf_torrents-0.0.1.post2311281817.dist-info/top_level.txt
hf_torrents-0.0.1.post2311281817.dist-info/zip-safe
hf_torrents-0.0.1.post2311281817.dist-info/RECORD
