Metadata-Version: 2.1
Name: hf-torrents
Version: 0.0.1-2311281817
Summary: A simple placeholder
Home-page: https://github.com/Lyken17/
Author: Ligeng Zhu
Author-email: ligeng.zhu+github@gmail.com
License: MIT
Platform: UNKNOWN
Classifier: Programming Language :: Python :: 3
License-File: LICENSE
Requires-Dist: torch
